basicanalysis
