Metadata-Version: 2.1
Name: basicanalysis
Version: 0.1.1
Summary: A quick way to see the best supervised learning method for your dataset or best configuration for the chosen method.
Home-page: https://github.com/niraljshah/SupervisedLearningOverview
Author: ['Niral J Shah']
Author-email: niraljshah@outlook.com
License: MIT
Keywords: Basic,Analysis,Supervised,Learning,Metrics,KNN,Adaboost,SVM,Naive-Bayes,Naive,Bayes,Logistic Regression,Logistic,Regression,Linear,Neural Network,Cross-validation,validation,k-fold,n-fold,10-fold,k-fold validation
Platform: UNKNOWN
